ndca/__init__.py
ndca/core.py
ndca/parser.py
ndca/serializer.py
ndca/utils.py
ndca-1.0.0.dist-info/licenses/LICENSE
ndca-1.0.0.dist-info/METADATA
ndca-1.0.0.dist-info/WHEEL
ndca-1.0.0.dist-info/top_level.txt
ndca-1.0.0.dist-info/RECORD
