Metadata-Version: 2.4
Name: ndca
Version: 1.0.0
Summary: NDCA (Nested Data Collection API) — a fast, safe, and human-readable nested data storage and manipulation library for Python.
Author: Viren Sahti
License: License & Disclaimer
Requires-Python: >=3.9
License-File: LICENSE
Dynamic: license-file
